mtxman/cli.py
mtxman/exceptions.py
mtxman/core/core.py
mtxman/core/dependencies.py
mtxman/deps/custom/graph500_generator_main.c
mtxman/downloaders/direct_url.py
mtxman/downloaders/suite_sparse.py
mtxman/generators/graph500.py
mtxman/generators/parmat.py
mtxman-0.0.8.dist-info/METADATA
mtxman-0.0.8.dist-info/WHEEL
mtxman-0.0.8.dist-info/entry_points.txt
mtxman-0.0.8.dist-info/top_level.txt
mtxman-0.0.8.dist-info/RECORD
