Metadata-Version: 2.4
Name: mtxman
Version: 0.0.8
Summary: A utility that simplifies the download and generation of Matrix Market (`.mtx`) files.
Author-email: Thomas Pasquali <thomas.pasquali@unitn.it>
Project-URL: Homepage, https://github.com/ThomasPasquali/MtxMan
Project-URL: Bug Tracker, https://github.com/ThomasPasquali/MtxMan/issues
Classifier: Programming Language :: Python :: 3
Classifier: License :: OSI Approved :: MIT License
Classifier: Operating System :: OS Independent
Requires-Python: >=3.8
Requires-Dist: typer[all]
Requires-Dist: rich
Requires-Dist: PyYAML
Requires-Dist: ssgetpy
Requires-Dist: beautifulsoup4
Requires-Dist: requests
